ebs/__init__.py
ebs/linuxnode/__init__.py
ebs/linuxnode/updater/__init__.py
ebs/linuxnode/updater/config.py
ebs/linuxnode/updater/log.py
ebs/linuxnode/updater/updater.py
ebs/linuxnode/updater/default/config.ini
ebs/linuxnode/updater/domains/__init__.py
ebs/linuxnode/updater/domains/base.py
ebs/linuxnode/updater/domains/pip.py
ebs_linuxnode_updater-0.1.3.dist-info/METADATA
ebs_linuxnode_updater-0.1.3.dist-info/WHEEL
ebs_linuxnode_updater-0.1.3.dist-info/entry_points.txt
ebs_linuxnode_updater-0.1.3.dist-info/top_level.txt
ebs_linuxnode_updater-0.1.3.dist-info/RECORD
