Metadata-Version: 2.1
Name: ebs-linuxnode-updater
Version: 0.1.3
Summary: Unattended self-updater for field-deployed embedded linux nodes
Home-page: UNKNOWN
Author: Chintalagiri Shashank
Author-email: shashank.chintalagiri@gmail.com
License: UNKNOWN
Platform: UNKNOWN
Classifier: Development Status :: 5 - Production/Stable
Classifier: Intended Audience :: Developers
Classifier: License :: OSI Approved :: GNU General Public License v3 or later (GPLv3+)
Classifier: Programming Language :: Python
Classifier: Programming Language :: Python :: 3
Classifier: Programming Language :: Python :: 3.6
Classifier: Operating System :: POSIX :: Linux
Requires-Dist: six
Requires-Dist: appdirs
Requires-Dist: setuptools-scm
Requires-Dist: loguru
